alice_colorscheme/__init__.py
alice_colorscheme/__main__.py
alice_colorscheme/cli.py
alice_colorscheme/palette.py
alice_colorscheme/util.py
alice_colorscheme-0.0.1.dist-info/METADATA
alice_colorscheme-0.0.1.dist-info/WHEEL
alice_colorscheme-0.0.1.dist-info/entry_points.txt
alice_colorscheme-0.0.1.dist-info/licenses/LICENSE
alice_colorscheme-0.0.1.dist-info/RECORD
