Metadata-Version: 2.4
Name: alice-colorscheme
Version: 0.0.1
Summary: Command-line tool for the alice color scheme
Project-URL: Homepage, https://github.com/wreedb/alice-cli
Project-URL: Issues, https://github.com/wreedb/alice-cli/issues
Author-email: Will Reed <wreed@programmer.net>
License-Expression: BSD-2-Clause
License-File: LICENSE
Classifier: Operating System :: OS Independent
Classifier: Programming Language :: Python :: 3
Classifier: Topic :: Utilities
Requires-Python: >=3.10
